kop/__init__.py
kop-0.0.1.dist-info/METADATA
kop-0.0.1.dist-info/WHEEL
kop-0.0.1.dist-info/top_level.txt
kop-0.0.1.dist-info/RECORD
