Metadata-Version: 2.1
Name: kop
Version: 0.0.1
Summary: Modern python kubernetes operators
Author-email: Alex Kwiatkowski <alex+pypi@fremantle.io>
License: MIT License
Project-URL: Homepage, https://github.com/rupurt/kop
Project-URL: Issues, https://github.com/rupurt/kop/issues
Classifier: Programming Language :: Python :: 3
Classifier: Operating System :: OS Independent
Requires-Python: >=3.12
Requires-Dist: jinja2 >=3.0.0
Requires-Dist: kopf >=1.37.0
Requires-Dist: kr8s >=0.17.0
Requires-Dist: kubernetes >=30.0.0
Requires-Dist: PyYAML ~=6.0.1
